MANIFEST.in
README.rst
TODO.rst
setup.py
RVirtualEnv.egg-info/PKG-INFO
RVirtualEnv.egg-info/SOURCES.txt
RVirtualEnv.egg-info/dependency_links.txt
RVirtualEnv.egg-info/entry_points.txt
RVirtualEnv.egg-info/not-zip-safe
RVirtualEnv.egg-info/top_level.txt
rvirtualenv/__init__.py
rvirtualenv/copy.py
rvirtualenv/generate.py
rvirtualenv/rvirtualenvinstall/__init__.py
rvirtualenv/rvirtualenvinstall/boot.py
rvirtualenv/rvirtualenvinstall/develop.py
rvirtualenv/rvirtualenvinstall/install.py
rvirtualenv/rvirtualenvinstall/scheme.py
rvirtualenv/template/inst/rvirtualenvkeep.py
rvirtualenv/template/inst/setup.py
rvirtualenv/template/inst/bin/activate
rvirtualenv/template/inst/bin/activate.bat
rvirtualenv/template/inst/bin/activate.bat.template
rvirtualenv/template/inst/bin/activate.py
rvirtualenv/template/inst/bin/activate.template
rvirtualenv/template/inst/bin/deactivate.bat
rvirtualenv/template/inst/bin/deactivate.bat.template
rvirtualenv/template/inst/bin/getpythondist.py
rvirtualenv/template/inst/bin/python
rvirtualenv/template/inst/bin/python.bat
rvirtualenv/template/inst/bin/python.py
rvirtualenv/template/venv/pythonrc.py
rvirtualenv/template/venv/site.py
rvirtualenv/template/venv/rvirtualenvinstall.egg-info/PKG-INFO
rvirtualenv/template/venv/rvirtualenvinstall.egg-info/entry_points.txt