Metadata-Version: 1.1
Name: RVirtualEnv
Version: 0.3.2
Summary: relocatable python virtual environment
Home-page: http://github.com/kvbik/rvirtualenv
Author: Jakub Vysoky
Author-email: jakub@borka.cz
License: BSD
Platform: UNKNOWN
Classifier: Development Status :: 4 - Beta
Classifier: Programming Language :: Python
Classifier: Programming Language :: Python :: 2
Classifier: Programming Language :: Python :: 3
Classifier: Intended Audience :: Developers
Classifier: License :: OSI Approved :: BSD License
Classifier: Operating System :: OS Independent
